ondemand_dask/__init__.py
ondemand_dask/core.py
ondemand_dask/function.py
ondemand_dask/install.sh
ondemand_dask/libraries.py
ondemand_dask/upload.py
ondemand_dask/image/docker-compose.yaml
ondemand_dask/image/dask/Dockerfile
ondemand_dask/image/dask/delete.py
ondemand_dask/image/dask/requirements.txt
ondemand_dask/image/dask/run.py
ondemand_dask-0.0.10.dist-info/LICENSE
ondemand_dask-0.0.10.dist-info/METADATA
ondemand_dask-0.0.10.dist-info/WHEEL
ondemand_dask-0.0.10.dist-info/top_level.txt
ondemand_dask-0.0.10.dist-info/RECORD
