Metadata-Version: 2.1
Name: ondemand-dask
Version: 0.0.10
Summary: Dask cluster on demand and automatically delete itself after expired. Only support GCP for now.
Home-page: https://github.com/kfit-dev/ondemand-dask
Author: huseinzol05
Author-email: husein.zol05@gmail.com
License: MIT
Platform: UNKNOWN
Classifier: Programming Language :: Python :: 3.7
Classifier: Intended Audience :: Developers
Classifier: License :: OSI Approved :: MIT License
Classifier: Operating System :: OS Independent
Requires-Python: >=3.6.*
Requires-Dist: requests
Requires-Dist: herpetologist
Requires-Dist: google-cloud-storage
Requires-Dist: google-api-python-client
Requires-Dist: cloudpickle
